sleeper_api/__init__.py
sleeper_api/client.py
sleeper_api/config.py
sleeper_api/exceptions.py
sleeper_api/persistent_cache.py
sleeper_api/utils.py
sleeper_api/endpoints/__init__.py
sleeper_api/endpoints/draft_endpoint.py
sleeper_api/endpoints/league_endpoint.py
sleeper_api/endpoints/nfl_endpoint.py
sleeper_api/endpoints/player_endpoint.py
sleeper_api/endpoints/projections_endpoint.py
sleeper_api/endpoints/user_endpoint.py
sleeper_api/models/__init__.py
sleeper_api/models/brackets.py
sleeper_api/models/draft.py
sleeper_api/models/league.py
sleeper_api/models/matchups.py
sleeper_api/models/nfl_state.py
sleeper_api/models/picks.py
sleeper_api/models/player.py
sleeper_api/models/roster.py
sleeper_api/models/schedule.py
sleeper_api/models/team_depth_chart.py
sleeper_api/models/traded_picks.py
sleeper_api/models/transactions.py
sleeper_api/models/user.py
sleeper_fantasy_api-0.3.0.dist-info/licenses/LICENSE.md
sleeper_fantasy_api-0.3.0.dist-info/METADATA
sleeper_fantasy_api-0.3.0.dist-info/WHEEL
sleeper_fantasy_api-0.3.0.dist-info/top_level.txt
sleeper_fantasy_api-0.3.0.dist-info/RECORD
