Metadata-Version: 2.4
Name: sleeper_fantasy_api
Version: 0.3.0
Summary: A Python wrapper for the Sleeper Fantasy API
Author-email: Samuel Mallery <mallerysam@gmail.com>
Maintainer-email: Samuel Mallery <mallerysam@gmail.com>
License: MIT
Project-URL: Homepage, https://github.com/smallery/sleeper_fantasy_api
Project-URL: Issues, https://github.com/smallery/sleeper_fantasy_api/issues
Keywords: sleeper,fantasy football,football,nfl,sleeper api,fantasy
Classifier: Programming Language :: Python :: 3
Classifier: License :: OSI Approved :: MIT License
Classifier: Operating System :: OS Independent
Requires-Python: >=3.10
License-File: LICENSE.md
Requires-Dist: platformdirs==3.8.1
Requires-Dist: requests==2.31.0
Requires-Dist: pytest==8.2.2
Dynamic: license-file
